Workbook

Sheet Лист2
A1: Личные вещи - Одежда, обувь, аксессуары - Мужская обувь - Кроссовки
A2: Id | B2: ListingFee | C2: AvitoId | D2: ContactPhone | E2: Address | F2: Title | G2: Description | H2: Price | I2: ImageUrls | J2: ContactMethod | K2: Category | L2: GoodsType | M2: Condition | N2: AdType | O2: Brand | P2: Color | Q2: ColorName | R2: MaterialsOdezhda | S2: MultiItem | T2: ApparelType | U2: Size | V2: CompanyName | W2: AvitoDateEnd | X2: AvitoStatus | Y2: EMail
A3: Обязательный | B3: Необязательный | C3: Необязательный | D3: Необязательный | E3: Обязательный | F3: Обязательный | G3: Обязательный | H3: Необязательный | I3: Обязательный | J3: Необязательный | K3: Обязательный | L3: Обязательный | M3: Обязательный | N3: Обязательный | O3: Обязательный | P3: Может быть обязательным_x000D_ Подробнее | Q3: Необязательный | R3: Необязательный | S3: Необязательный | T3: Обязательный | U3: Обязательный
A4: Подробнее о параметре | B4: Одно значение из выпадающего списка в ячейке | C4: Подробнее о параметре | D4: Подробнее о параметре | E4: Подробнее о параметре | F4: Подробнее о параметре | G4: Подробнее о параметре | H4: Подробнее о параметре | I4: Подробнее о параметре | J4: Одно значение из выпадающего списка в ячейке | K4: Одно значение из выпадающего списка в ячейке | L4: Одно значение из выпадающего списка в ячейке | M4: Одно значение из выпадающего списка в ячейке | N4: Одно значение из выпадающего списка в ячейке | O4: Одно значение из листа Спр-Мужская обувь-Кроссовки | P4: Одно значение из выпадающего списка в ячейке | Q4: Подробнее о параметре | R4: Одно или несколько значений из выпадающего списка в ячейке | S4: Одно значение из выпадающего списка в ячейке | T4: Одно значение из выпадающего списка в ячейке | U4: Одно значение из выпадающего списка в ячейке
A5: ='[1]Основной сток'!A2 -> 1338233 | B5: Package | D5: 79030042191 | E5: Варшавское ш., 9с1 | F5: =PROPER(LEFT('[1]Основной сток'!I2,FIND(CHAR(10),'[1]Основной сток'!I2&CHAR(10))-1)) -> Nike Dunk Low Retro Black Hyper Cobalt | G5: =F5 & ", " & '[1]Основной сток'!H2 & CHAR(10) & "• В наличии в Москве" & CHAR(10) & "• Оригинал, можно проверить при получении" & CHAR(10) & "• Совершенно новые, полный комплект" & CHAR(10) & "• Размер: EU " & '[1]Основной сток'!J2 & " / RU " & INDEX('[1]Размерная сетка'!$B$2:$B$40,MATCH('[1]Основной сток'!J2,'[1]Размерная сетка'!$A$2:$A$40,0)) & " / US " & INDEX('[1]Размерная сетка'!$C$2:$C$40,MATCH('[1]Основной сток'!J2,'[1]Размерная сетка'!$A$2:$A$40,0)) & " / см " & INDEX('[1]Размерная сетка'!$D$2:$D$40,MATCH('[1]Основной сток'!J2,'[1]Размерная сетка'!$A$2:$A$40,0)) & CHAR(10) & "• Посадка: размер в размер" & CHAR(10) & CHAR(10) & "🚚 Авито Доставка — по всей России" & CHAR(10) & "📍 Самовывоз — Москва, м. Тульская, Даниловская мануфактура" & CHAR(10) & CHAR(10) & "По любым вопросам пишите в личные сообщения — все расскажем и поможем выбрать размер 👟" -> Nike Dunk Low Retro Black Hyper Cobalt, DD1391-001 • В наличии в Москве • Оригинал, можно проверить при получении • Совершенно новые, полный комплект • Размер: EU 43 / RU 42 / US 9,5 / см 27 • Посадка: размер в размер 🚚 Авито Доставка — по всей России 📍 Самовывоз — Москва, м. Тульская, Даниловская мануфактура По любым вопросам пишите в личные сообщения — все расскажем и поможем выбрать размер 👟 | H5: ='[1]Основной сток'!L2 -> 9000 | I5: {=VLOOKUP(INDEX('[1]Основной сток'!H:H,ROW()-3),[1]Фотки!A:B,2,FALSE)} -> https://i.ibb.co/RtyzMvw/1-1.jpg | J5: В сообщениях | K5: Одежда, обувь, аксессуары | L5: =IF(U5<=40,"Женская обувь","Мужская обувь") -> Мужская обувь | M5: Новое с биркой | N5: Товар приобретен на продажу | O5: =PROPER('[1]Основной сток'!F2) -> Nike | P5: ='[1]Основной сток'!M2 -> Синий | Q5: Черно-синий | R5: Натуральная кожа | S5: Да | T5: =IF(L5="Мужская обувь","Кроссовки","Кроссовки и кеды") -> Кроссовки | U5: ='[1]Основной сток'!J2 - 1 -> 42 | V5: sold twice | X5: Активно | Y5: soldsoldtwice@gmail.com
A6: ='[1]Основной сток'!A3 -> 1342231 | B6: Package | D6: 79030042191 | E6: Варшавское ш., 9с1 | F6: =PROPER(LEFT('[1]Основной сток'!I3,FIND(CHAR(10),'[1]Основной сток'!I3&CHAR(10))-1)) -> Jordan 1 Mid Light Smoke Grey (Gs) | G6: =F6 & ", " & '[1]Основной сток'!H3 & CHAR(10) & "• В наличии в Москве" & CHAR(10) & "• Оригинал, можно проверить при получении" & CHAR(10) & "• Совершенно новые, полный комплект" & CHAR(10) & "• Размер: EU " & '[1]Основной сток'!J3 & " / RU " & INDEX('[1]Размерная сетка'!$B$2:$B$40,MATCH('[1]Основной сток'!J3,'[1]Размерная сетка'!$A$2:$A$40,0)) & " / US " & INDEX('[1]Размерная сетка'!$C$2:$C$40,MATCH('[1]Основной сток'!J3,'[1]Размерная сетка'!$A$2:$A$40,0)) & " / см " & INDEX('[1]Размерная сетка'!$D$2:$D$40,MATCH('[1]Основной сток'!J3,'[1]Размерная сетка'!$A$2:$A$40,0)) & CHAR(10) & "• Посадка: размер в размер" & CHAR(10) & CHAR(10) & "🚚 Авито Доставка — по всей России" & CHAR(10) & "📍 Самовывоз — Москва, м. Тульская, Даниловская мануфактура" & CHAR(10) & CHAR(10) & "По любым вопросам пишите в личные сообщения — все расскажем и поможем выбрать размер 👟" -> Jordan 1 Mid Light Smoke Grey (Gs), 554725-078 • В наличии в Москве • Оригинал, можно проверить при получении • Совершенно новые, полный комплект • Размер: EU 38,5 / RU 37,5 / US 7,5 / см 24 • Посадка: размер в размер 🚚 Авито Доставка — по всей России 📍 Самовывоз — Москва, м. Тульская, Даниловская мануфактура По любым вопросам пишите в личные сообщения — все расскажем и поможем выбрать размер 👟 | H6: ='[1]Основной сток'!L3 -> 13900 | I6: {=VLOOKUP(INDEX('[1]Основной сток'!H:H,ROW()-3),[1]Фотки!A:B,2,FALSE)} -> https://i.ibb.co/97jv6VD/1.jpg | J6: В сообщениях | K6: Одежда, обувь, аксессуары | L6: =IF(U6<=40,"Женская обувь","Мужская обувь") -> Женская обувь | M6: Новое с биркой | N6: Товар приобретен на продажу | O6: =PROPER('[1]Основной сток'!F3) -> Jordan | P6: ='[1]Основной сток'!M3 -> Серый | Q6: Smoke grey/white/anthracite | R6: Натуральная кожа | S6: Да | T6: =IF(L6="Мужская обувь","Кроссовки","Кроссовки и кеды") -> Кроссовки и кеды | U6: ='[1]Основной сток'!J3 - 1 -> 37.5 | V6: sold twice | X6: Активно | Y6: soldsoldtwice@gmail.com
A7: ='[1]Основной сток'!A4 -> 1342235 | B7: Package | D7: 79030042191 | E7: Варшавское ш., 9с1 | F7: =PROPER(LEFT('[1]Основной сток'!I4,FIND(CHAR(10),'[1]Основной сток'!I4&CHAR(10))-1)) -> Jordan 1 Retro High Og Brotherhood | G7: =F7 & ", " & '[1]Основной сток'!H4 & CHAR(10) & "• В наличии в Москве" & CHAR(10) & "• Оригинал, можно проверить при получении" & CHAR(10) & "• Совершенно новые, полный комплект" & CHAR(10) & "• Размер: EU " & '[1]Основной сток'!J4 & " / RU " & INDEX('[1]Размерная сетка'!$B$2:$B$40,MATCH('[1]Основной сток'!J4,'[1]Размерная сетка'!$A$2:$A$40,0)) & " / US " & INDEX('[1]Размерная сетка'!$C$2:$C$40,MATCH('[1]Основной сток'!J4,'[1]Размерная сетка'!$A$2:$A$40,0)) & " / см " & INDEX('[1]Размерная сетка'!$D$2:$D$40,MATCH('[1]Основной сток'!J4,'[1]Размерная сетка'!$A$2:$A$40,0)) & CHAR(10) & "• Посадка: размер в размер" & CHAR(10) & CHAR(10) & "🚚 Авито Доставка — по всей России" & CHAR(10) & "📍 Самовывоз — Москва, м. Тульская, Даниловская мануфактура" & CHAR(10) & CHAR(10) & "По любым вопросам пишите в личные сообщения — все расскажем и поможем выбрать размер 👟" -> Jordan 1 Retro High Og Brotherhood, 555088-706 • В наличии в Москве • Оригинал, можно проверить при получении • Совершенно новые, полный комплект • Размер: EU 45,5 / RU 44,5 / US 11,5 / см 28,7 • Посадка: размер в размер 🚚 Авито Доставка — по всей России 📍 Самовывоз — Москва, м. Тульская, Даниловская мануфактура По любым вопросам пишите в личные сообщения — все расскажем и поможем выбрать размер 👟 | H7: ='[1]Основной сток'!L4 -> 13000 | I7: {=VLOOKUP(INDEX('[1]Основной сток'!H:H,ROW()-3),[1]Фотки!A:B,2,FALSE)} -> https://i.ibb.co/GmTzTmR/1.jpg|https://i.ibb.co/1ftfc8bw/2.jpg|https://i.ibb.co/VGfs7w9/3.jpg|https://i.ibb.co/LDhjyWKt/4.jpg | J7: В сообщениях | K7: Одежда, обувь, аксессуары | L7: =IF(U7<=40,"Женская обувь","Мужская обувь") -> Мужская обувь | M7: Новое с биркой | N7: Товар приобретен на продажу | O7: =PROPER('[1]Основной сток'!F4) -> Jordan | P7: ='[1]Основной сток'!M4 -> Желтый | R7: Натуральная кожа | S7: Да | T7: =IF(L7="Мужская обувь","Кроссовки","Кроссовки и кеды") -> Кроссовки | U7: ='[1]Основной сток'!J4 - 1 -> 44.5 | V7: sold twice | X7: Активно | Y7: soldsoldtwice@gmail.com
A8: ='[1]Основной сток'!A5 -> 1342237 | B8: Package | D8: 79030042191 | E8: Варшавское ш., 9с1 | F8: =PROPER(LEFT('[1]Основной сток'!I5,FIND(CHAR(10),'[1]Основной сток'!I5&CHAR(10))-1)) -> Jordan 1 Retro High Og Brotherhood (Gs) | G8: =F8 & ", " & '[1]Основной сток'!H5 & CHAR(10) & "• В наличии в Москве" & CHAR(10) & "• Оригинал, можно проверить при получении" & CHAR(10) & "• Совершенно новые, полный комплект" & CHAR(10) & "• Размер: EU " & '[1]Основной сток'!J5 & " / RU " & INDEX('[1]Размерная сетка'!$B$2:$B$40,MATCH('[1]Основной сток'!J5,'[1]Размерная сетка'!$A$2:$A$40,0)) & " / US " & INDEX('[1]Размерная сетка'!$C$2:$C$40,MATCH('[1]Основной сток'!J5,'[1]Размерная сетка'!$A$2:$A$40,0)) & " / см " & INDEX('[1]Размерная сетка'!$D$2:$D$40,MATCH('[1]Основной сток'!J5,'[1]Размерная сетка'!$A$2:$A$40,0)) & CHAR(10) & "• Посадка: размер в размер" & CHAR(10) & CHAR(10) & "🚚 Авито Доставка — по всей России" & CHAR(10) & "📍 Самовывоз — Москва, м. Тульская, Даниловская мануфактура" & CHAR(10) & CHAR(10) & "По любым вопросам пишите в личные сообщения — все расскажем и поможем выбрать размер 👟" -> Jordan 1 Retro High Og Brotherhood (Gs), 575441-706 • В наличии в Москве • Оригинал, можно проверить при получении • Совершенно новые, полный комплект • Размер: EU 36,5 / RU 35,5 / US 6 / см 22,7 • Посадка: размер в размер 🚚 Авито Доставка — по всей России 📍 Самовывоз — Москва, м. Тульская, Даниловская мануфактура По любым вопросам пишите в личные сообщения — все расскажем и поможем выбрать размер 👟 | H8: ='[1]Основной сток'!L5 -> 11900 | I8: {=VLOOKUP(INDEX('[1]Основной сток'!H:H,ROW()-3),[1]Фотки!A:B,2,FALSE)} -> https://i.ibb.co/GmTzTmR/1.jpg|https://i.ibb.co/1ftfc8bw/2.jpg|https://i.ibb.co/VGfs7w9/3.jpg|https://i.ibb.co/LDhjyWKt/4.jpg | J8: В сообщениях | K8: Одежда, обувь, аксессуары | L8: =IF(U8<=40,"Женская обувь","Мужская обувь") -> Женская обувь | M8: Новое с биркой | N8: Товар приобретен на продажу | O8: =PROPER('[1]Основной сток'!F5) -> Jordan | P8: ='[1]Основной сток'!M5 -> Желтый | R8: Натуральная кожа | S8: Да | T8: =IF(L8="Мужская обувь","Кроссовки","Кроссовки и кеды") -> Кроссовки и кеды | U8: ='[1]Основной сток'!J5 - 1 -> 35.5 | V8: sold twice | X8: Активно | Y8: soldsoldtwice@gmail.com
A9: ='[1]Основной сток'!A6 -> 1342243 | B9: Package | D9: 79030042191 | E9: Варшавское ш., 9с1 | F9: =PROPER(LEFT('[1]Основной сток'!I6,FIND(CHAR(10),'[1]Основной сток'!I6&CHAR(10))-1)) -> Jordan 1 Mid Wolf Grey Aluminum (W) | G9: =F9 & ", " & '[1]Основной сток'!H6 & CHAR(10) & "• В наличии в Москве" & CHAR(10) & "• Оригинал, можно проверить при получении" & CHAR(10) & "• Совершенно новые, полный комплект" & CHAR(10) & "• Размер: EU " & '[1]Основной сток'!J6 & " / RU " & INDEX('[1]Размерная сетка'!$B$2:$B$40,MATCH('[1]Основной сток'!J6,'[1]Размерная сетка'!$A$2:$A$40,0)) & " / US " & INDEX('[1]Размерная сетка'!$C$2:$C$40,MATCH('[1]Основной сток'!J6,'[1]Размерная сетка'!$A$2:$A$40,0)) & " / см " & INDEX('[1]Размерная сетка'!$D$2:$D$40,MATCH('[1]Основной сток'!J6,'[1]Размерная сетка'!$A$2:$A$40,0)) & CHAR(10) & "• Посадка: размер в размер" & CHAR(10) & CHAR(10) & "🚚 Авито Доставка — по всей России" & CHAR(10) & "📍 Самовывоз — Москва, м. Тульская, Даниловская мануфактура" & CHAR(10) & CHAR(10) & "По любым вопросам пишите в личные сообщения — все расскажем и поможем выбрать размер 👟" -> Jordan 1 Mid Wolf Grey Aluminum (W), BQ6472-105 • В наличии в Москве • Оригинал, можно проверить при получении • Совершенно новые, полный комплект • Размер: EU 36,5 / RU 35,5 / US 6 / см 22,7 • Посадка: размер в размер 🚚 Авито Доставка — по всей России 📍 Самовывоз — Москва, м. Тульская, Даниловская мануфактура По любым вопросам пишите в личные сообщения — все расскажем и поможем выбрать размер 👟 | H9: ='[1]Основной сток'!L6 -> 13000 | I9: {=VLOOKUP(INDEX('[1]Основной сток'!H:H,ROW()-3),[1]Фотки!A:B,2,FALSE)} -> https://i.ibb.co/Q7NPYXDQ/1-1.jpg|https://i.ibb.co/QFSwP6Bh/2.jpg|https://i.ibb.co/qLN13WhF/3.jpg|https://i.ibb.co/G3t7VY73/4.jpg | J9: В сообщениях | K9: Одежда, обувь, аксессуары | L9: =IF(U9<=40,"Женская обувь","Мужская обувь") -> Женская обувь | M9: Новое с биркой | N9: Товар приобретен на продажу | O9: =PROPER('[1]Основной сток'!F6) -> Jordan | P9: ='[1]Основной сток'!M6 -> Серый | R9: Натуральная кожа | S9: Да | T9: =IF(L9="Мужская обувь","Кроссовки","Кроссовки и кеды") -> Кроссовки и кеды | U9: ='[1]Основной сток'!J6 - 1 -> 35.5 | V9: sold twice | X9: Активно | Y9: soldsoldtwice@gmail.com
A10: ='[1]Основной сток'!A7 -> 1342244 | B10: Package | D10: 79030042191 | E10: Варшавское ш., 9с1 | F10: =PROPER(LEFT('[1]Основной сток'!I7,FIND(CHAR(10),'[1]Основной сток'!I7&CHAR(10))-1)) -> Jordan 1 Mid Wolf Grey Aluminum (W) | G10: =F10 & ", " & '[1]Основной сток'!H7 & CHAR(10) & "• В наличии в Москве" & CHAR(10) & "• Оригинал, можно проверить при получении" & CHAR(10) & "• Совершенно новые, полный комплект" & CHAR(10) & "• Размер: EU " & '[1]Основной сток'!J7 & " / RU " & INDEX('[1]Размерная сетка'!$B$2:$B$40,MATCH('[1]Основной сток'!J7,'[1]Размерная сетка'!$A$2:$A$40,0)) & " / US " & INDEX('[1]Размерная сетка'!$C$2:$C$40,MATCH('[1]Основной сток'!J7,'[1]Размерная сетка'!$A$2:$A$40,0)) & " / см " & INDEX('[1]Размерная сетка'!$D$2:$D$40,MATCH('[1]Основной сток'!J7,'[1]Размерная сетка'!$A$2:$A$40,0)) & CHAR(10) & "• Посадка: размер в размер" & CHAR(10) & CHAR(10) & "🚚 Авито Доставка — по всей России" & CHAR(10) & "📍 Самовывоз — Москва, м. Тульская, Даниловская мануфактура" & CHAR(10) & CHAR(10) & "По любым вопросам пишите в личные сообщения — все расскажем и поможем выбрать размер 👟" -> Jordan 1 Mid Wolf Grey Aluminum (W), BQ6472-105 • В наличии в Москве • Оригинал, можно проверить при получении • Совершенно новые, полный комплект • Размер: EU 37,5 / RU 36,5 / US 6,5-7 / см 23,3 • Посадка: размер в размер 🚚 Авито Доставка — по всей России 📍 Самовывоз — Москва, м. Тульская, Даниловская мануфактура По любым вопросам пишите в личные сообщения — все расскажем и поможем выбрать размер 👟 | H10: ='[1]Основной сток'!L7 -> 13000 | I10: {=VLOOKUP(INDEX('[1]Основной сток'!H:H,ROW()-3),[1]Фотки!A:B,2,FALSE)} -> https://i.ibb.co/Q7NPYXDQ/1-1.jpg|https://i.ibb.co/QFSwP6Bh/2.jpg|https://i.ibb.co/qLN13WhF/3.jpg|https://i.ibb.co/G3t7VY73/4.jpg | J10: В сообщениях | K10: Одежда, обувь, аксессуары | L10: =IF(U10<=40,"Женская обувь","Мужская обувь") -> Женская обувь | M10: Новое с биркой | N10: Товар приобретен на продажу | O10: =PROPER('[1]Основной сток'!F7) -> Jordan | P10: ='[1]Основной сток'!M7 -> Серый | R10: Натуральная кожа | S10: Да | T10: =IF(L10="Мужская обувь","Кроссовки","Кроссовки и кеды") -> Кроссовки и кеды | U10: ='[1]Основной сток'!J7 - 1 -> 36.5 | V10: sold twice | X10: Активно | Y10: soldsoldtwice@gmail.com
A11: ='[1]Основной сток'!A8 -> 1342253 | B11: Package | D11: 79030042191 | E11: Варшавское ш., 9с1 | F11: =PROPER(LEFT('[1]Основной сток'!I8,FIND(CHAR(10),'[1]Основной сток'!I8&CHAR(10))-1)) -> Jordan 1 Mid Burgundy Dusty Pink | G11: =F11 & ", " & '[1]Основной сток'!H8 & CHAR(10) & "• В наличии в Москве" & CHAR(10) & "• Оригинал, можно проверить при получении" & CHAR(10) & "• Совершенно новые, полный комплект" & CHAR(10) & "• Размер: EU " & '[1]Основной сток'!J8 & " / RU " & INDEX('[1]Размерная сетка'!$B$2:$B$40,MATCH('[1]Основной сток'!J8,'[1]Размерная сетка'!$A$2:$A$40,0)) & " / US " & INDEX('[1]Размерная сетка'!$C$2:$C$40,MATCH('[1]Основной сток'!J8,'[1]Размерная сетка'!$A$2:$A$40,0)) & " / см " & INDEX('[1]Размерная сетка'!$D$2:$D$40,MATCH('[1]Основной сток'!J8,'[1]Размерная сетка'!$A$2:$A$40,0)) & CHAR(10) & "• Посадка: размер в размер" & CHAR(10) & CHAR(10) & "🚚 Авито Доставка — по всей России" & CHAR(10) & "📍 Самовывоз — Москва, м. Тульская, Даниловская мануфактура" & CHAR(10) & CHAR(10) & "По любым вопросам пишите в личные сообщения — все расскажем и поможем выбрать размер 👟" -> Jordan 1 Mid Burgundy Dusty Pink, BQ6472-202 • В наличии в Москве • Оригинал, можно проверить при получении • Совершенно новые, полный комплект • Размер: EU 36,5 / RU 35,5 / US 6 / см 22,7 • Посадка: размер в размер 🚚 Авито Доставка — по всей России 📍 Самовывоз — Москва, м. Тульская, Даниловская мануфактура По любым вопросам пишите в личные сообщения — все расскажем и поможем выбрать размер 👟 | H11: ='[1]Основной сток'!L8 -> 8900 | I11: {=VLOOKUP(INDEX('[1]Основной сток'!H:H,ROW()-3),[1]Фотки!A:B,2,FALSE)} -> https://i.ibb.co/BHgDYfkS/1.jpg | J11: В сообщениях | K11: Одежда, обувь, аксессуары | L11: =IF(U11<=40,"Женская обувь","Мужская обувь") -> Женская обувь | M11: Новое с биркой | N11: Товар приобретен на продажу | O11: =PROPER('[1]Основной сток'!F8) -> Jordan | P11: ='[1]Основной сток'!M8 -> Розовый | R11: Натуральная кожа | S11: Да | T11: =IF(L11="Мужская обувь","Кроссовки","Кроссовки и кеды") -> Кроссовки и кеды | U11: ='[1]Основной сток'!J8 - 1 -> 35.5 | V11: sold twice | X11: Активно | Y11: soldsoldtwice@gmail.com
A12: ='[1]Основной сток'!A9 -> 1342266 | B12: Package | D12: 79030042191 | E12: Варшавское ш., 9с1 | F12: =PROPER(LEFT('[1]Основной сток'!I9,FIND(CHAR(10),'[1]Основной сток'!I9&CHAR(10))-1)) -> Jordan 1 Retro High Lucky Green (W) | G12: =F12 & ", " & '[1]Основной сток'!H9 & CHAR(10) & "• В наличии в Москве" & CHAR(10) & "• Оригинал, можно проверить при получении" & CHAR(10) & "• Совершенно новые, полный комплект" & CHAR(10) & "• Размер: EU " & '[1]Основной сток'!J9 & " / RU " & INDEX('[1]Размерная сетка'!$B$2:$B$40,MATCH('[1]Основной сток'!J9,'[1]Размерная сетка'!$A$2:$A$40,0)) & " / US " & INDEX('[1]Размерная сетка'!$C$2:$C$40,MATCH('[1]Основной сток'!J9,'[1]Размерная сетка'!$A$2:$A$40,0)) & " / см " & INDEX('[1]Размерная сетка'!$D$2:$D$40,MATCH('[1]Основной сток'!J9,'[1]Размерная сетка'!$A$2:$A$40,0)) & CHAR(10) & "• Посадка: размер в размер" & CHAR(10) & CHAR(10) & "🚚 Авито Доставка — по всей России" & CHAR(10) & "📍 Самовывоз — Москва, м. Тульская, Даниловская мануфактура" & CHAR(10) & CHAR(10) & "По любым вопросам пишите в личные сообщения — все расскажем и поможем выбрать размер 👟" -> Jordan 1 Retro High Lucky Green (W), DB4612-300 • В наличии в Москве • Оригинал, можно проверить при получении • Совершенно новые, полный комплект • Размер: EU 36,5 / RU 35,5 / US 6 / см 22,7 • Посадка: размер в размер 🚚 Авито Доставка — по всей России 📍 Самовывоз — Москва, м. Тульская, Даниловская мануфактура По любым вопросам пишите в личные сообщения — все расскажем и поможем выбрать размер 👟 | H12: ='[1]Основной сток'!L9 -> 18000 | I12: {=VLOOKUP(INDEX('[1]Основной сток'!H:H,ROW()-3),[1]Фотки!A:B,2,FALSE)} -> https://i.ibb.co/fLsTwk5/1-1.jpg|https://i.ibb.co/MDxGwbfb/2.jpg|https://i.ibb.co/KcjFTP7w/4.jpg|https://i.ibb.co/0dyFgNB/DB4612-300.jpg | J12: В сообщениях | K12: Одежда, обувь, аксессуары | L12: =IF(U12<=40,"Женская обувь","Мужская обувь") -> Женская обувь | M12: Новое с биркой | N12: Товар приобретен на продажу | O12: =PROPER('[1]Основной сток'!F9) -> Jordan | P12: ='[1]Основной сток'!M9 -> Зелёный | R12: Натуральная кожа | S12: Да | T12: =IF(L12="Мужская обувь","Кроссовки","Кроссовки и кеды") -> Кроссовки и кеды | U12: ='[1]Основной сток'!J9 - 1 -> 35.5 | V12: sold twice | X12: Активно | Y12: soldsoldtwice@gmail.com
A13: ='[1]Основной сток'!A10 -> 1342278 | B13: Package | D13: 79030042191 | E13: Варшавское ш., 9с1 | F13: =PROPER(LEFT('[1]Основной сток'!I10,FIND(CHAR(10),'[1]Основной сток'!I10&CHAR(10))-1)) -> Jordan 1 Mid Se Light Mulberry (W) | G13: =F13 & ", " & '[1]Основной сток'!H10 & CHAR(10) & "• В наличии в Москве" & CHAR(10) & "• Оригинал, можно проверить при получении" & CHAR(10) & "• Совершенно новые, полный комплект" & CHAR(10) & "• Размер: EU " & '[1]Основной сток'!J10 & " / RU " & INDEX('[1]Размерная сетка'!$B$2:$B$40,MATCH('[1]Основной сток'!J10,'[1]Размерная сетка'!$A$2:$A$40,0)) & " / US " & INDEX('[1]Размерная сетка'!$C$2:$C$40,MATCH('[1]Основной сток'!J10,'[1]Размерная сетка'!$A$2:$A$40,0)) & " / см " & INDEX('[1]Размерная сетка'!$D$2:$D$40,MATCH('[1]Основной сток'!J10,'[1]Размерная сетка'!$A$2:$A$40,0)) & CHAR(10) & "• Посадка: размер в размер" & CHAR(10) & CHAR(10) & "🚚 Авито Доставка — по всей России" & CHAR(10) & "📍 Самовывоз — Москва, м. Тульская, Даниловская мануфактура" & CHAR(10) & CHAR(10) & "По любым вопросам пишите в личные сообщения — все расскажем и поможем выбрать размер 👟" -> Jordan 1 Mid Se Light Mulberry (W), DC7267-500 • В наличии в Москве • Оригинал, можно проверить при получении • Совершенно новые, полный комплект • Размер: EU 39 / RU 38 / US 8 / см 24,5 • Посадка: размер в размер 🚚 Авито Доставка — по всей России 📍 Самовывоз — Москва, м. Тульская, Даниловская мануфактура По любым вопросам пишите в личные сообщения — все расскажем и поможем выбрать размер 👟 | H13: ='[1]Основной сток'!L10 -> 13000 | I13: {=VLOOKUP(INDEX('[1]Основной сток'!H:H,ROW()-3),[1]Фотки!A:B,2,FALSE)} -> https://i.ibb.co/rRHj48Tx/1.jpg | J13: В сообщениях | K13: Одежда, обувь, аксессуары | L13: =IF(U13<=40,"Женская обувь","Мужская обувь") -> Женская обувь | M13: Новое с биркой | N13: Товар приобретен на продажу | O13: =PROPER('[1]Основной сток'!F10) -> Jordan | P13: ='[1]Основной сток'!M10 -> Розовый | R13: Натуральная кожа | S13: Да | T13: =IF(L13="Мужская обувь","Кроссовки","Кроссовки и кеды") -> Кроссовки и кеды | U13: ='[1]Основной сток'!J10 - 1 -> 38 | V13: sold twice | X13: Активно | Y13: soldsoldtwice@gmail.com
A14: ='[1]Основной сток'!A11 -> 1342280 | B14: Package | D14: 79030042191 | E14: Варшавское ш., 9с1 | F14: =PROPER(LEFT('[1]Основной сток'!I11,FIND(CHAR(10),'[1]Основной сток'!I11&CHAR(10))-1)) -> Jordan 1 Mid Se Light Mulberry (W) | G14: =F14 & ", " & '[1]Основной сток'!H11 & CHAR(10) & "• В наличии в Москве" & CHAR(10) & "• Оригинал, можно проверить при получении" & CHAR(10) & "• Совершенно новые, полный комплект" & CHAR(10) & "• Размер: EU " & '[1]Основной сток'!J11 & " / RU " & INDEX('[1]Размерная сетка'!$B$2:$B$40,MATCH('[1]Основной сток'!J11,'[1]Размерная сетка'!$A$2:$A$40,0)) & " / US " & INDEX('[1]Размерная сетка'!$C$2:$C$40,MATCH('[1]Основной сток'!J11,'[1]Размерная сетка'!$A$2:$A$40,0)) & " / см " & INDEX('[1]Размерная сетка'!$D$2:$D$40,MATCH('[1]Основной сток'!J11,'[1]Размерная сетка'!$A$2:$A$40,0)) & CHAR(10) & "• Посадка: размер в размер" & CHAR(10) & CHAR(10) & "🚚 Авито Доставка — по всей России" & CHAR(10) & "📍 Самовывоз — Москва, м. Тульская, Даниловская мануфактура" & CHAR(10) & CHAR(10) & "По любым вопросам пишите в личные сообщения — все расскажем и поможем выбрать размер 👟" -> Jordan 1 Mid Se Light Mulberry (W), DC7267-500 • В наличии в Москве • Оригинал, можно проверить при получении • Совершенно новые, полный комплект • Размер: EU 40,5 / RU 39,5 / US 9 / см 25,3 • Посадка: размер в размер 🚚 Авито Доставка — по всей России 📍 Самовывоз — Москва, м. Тульская, Даниловская мануфактура По любым вопросам пишите в личные сообщения — все расскажем и поможем выбрать размер 👟 | H14: ='[1]Основной сток'!L11 -> 13000 | I14: {=VLOOKUP(INDEX('[1]Основной сток'!H:H,ROW()-3),[1]Фотки!A:B,2,FALSE)} -> https://i.ibb.co/rRHj48Tx/1.jpg | J14: В сообщениях | K14: Одежда, обувь, аксессуары | L14: =IF(U14<=40,"Женская обувь","Мужская обувь") -> Женская обувь | M14: Новое с биркой | N14: Товар приобретен на продажу | O14: =PROPER('[1]Основной сток'!F11) -> Jordan | P14: ='[1]Основной сток'!M11 -> Розовый | R14: Натуральная кожа | S14: Да | T14: =IF(L14="Мужская обувь","Кроссовки","Кроссовки и кеды") -> Кроссовки и кеды | U14: ='[1]Основной сток'!J11 - 1 -> 39.5 | V14: sold twice | X14: Активно | Y14: soldsoldtwice@gmail.com
A15: ='[1]Основной сток'!A12 -> 1342283 | B15: Package | D15: 79030042191 | E15: Варшавское ш., 9с1 | F15: =PROPER(LEFT('[1]Основной сток'!I12,FIND(CHAR(10),'[1]Основной сток'!I12&CHAR(10))-1)) -> Jordan 1 Mid Se Arctic Pink (Gs) | G15: =F15 & ", " & '[1]Основной сток'!H12 & CHAR(10) & "• В наличии в Москве" & CHAR(10) & "• Оригинал, можно проверить при получении" & CHAR(10) & "• Совершенно новые, полный комплект" & CHAR(10) & "• Размер: EU " & '[1]Основной сток'!J12 & " / RU " & INDEX('[1]Размерная сетка'!$B$2:$B$40,MATCH('[1]Основной сток'!J12,'[1]Размерная сетка'!$A$2:$A$40,0)) & " / US " & INDEX('[1]Размерная сетка'!$C$2:$C$40,MATCH('[1]Основной сток'!J12,'[1]Размерная сетка'!$A$2:$A$40,0)) & " / см " & INDEX('[1]Размерная сетка'!$D$2:$D$40,MATCH('[1]Основной сток'!J12,'[1]Размерная сетка'!$A$2:$A$40,0)) & CHAR(10) & "• Посадка: размер в размер" & CHAR(10) & CHAR(10) & "🚚 Авито Доставка — по всей России" & CHAR(10) & "📍 Самовывоз — Москва, м. Тульская, Даниловская мануфактура" & CHAR(10) & CHAR(10) & "По любым вопросам пишите в личные сообщения — все расскажем и поможем выбрать размер 👟" -> Jordan 1 Mid Se Arctic Pink (Gs), DC9617-600 • В наличии в Москве • Оригинал, можно проверить при получении • Совершенно новые, полный комплект • Размер: EU 38 / RU 37 / US 7 / см 23,5 • Посадка: размер в размер 🚚 Авито Доставка — по всей России 📍 Самовывоз — Москва, м. Тульская, Даниловская мануфактура По любым вопросам пишите в личные сообщения — все расскажем и поможем выбрать размер 👟 | H15: ='[1]Основной сток'!L12 -> 12900 | I15: {=VLOOKUP(INDEX('[1]Основной сток'!H:H,ROW()-3),[1]Фотки!A:B,2,FALSE)} -> https://i.ibb.co/cS3p7Lbs/1.jpg | J15: В сообщениях | K15: Одежда, обувь, аксессуары | L15: =IF(U15<=40,"Женская обувь","Мужская обувь") -> Женская обувь | M15: Новое с биркой | N15: Товар приобретен на продажу | O15: =PROPER('[1]Основной сток'!F12) -> Jordan | P15: ='[1]Основной сток'!M12 -> Розовый | R15: Натуральная кожа | S15: Да | T15: =IF(L15="Мужская обувь","Кроссовки","Кроссовки и кеды") -> Кроссовки и кеды | U15: ='[1]Основной сток'!J12 - 1 -> 37 | V15: sold twice | X15: Активно | Y15: soldsoldtwice@gmail.com
A16: ='[1]Основной сток'!A13 -> 1342289 | B16: Package | D16: 79030042191 | E16: Варшавское ш., 9с1 | F16: =PROPER(LEFT('[1]Основной сток'!I13,FIND(CHAR(10),'[1]Основной сток'!I13&CHAR(10))-1)) -> Nike Dunk Low Easter 2022 (W) | G16: =F16 & ", " & '[1]Основной сток'!H13 & CHAR(10) & "• В наличии в Москве" & CHAR(10) & "• Оригинал, можно проверить при получении" & CHAR(10) & "• Совершенно новые, полный комплект" & CHAR(10) & "• Размер: EU " & '[1]Основной сток'!J13 & " / RU " & INDEX('[1]Размерная сетка'!$B$2:$B$40,MATCH('[1]Основной сток'!J13,'[1]Размерная сетка'!$A$2:$A$40,0)) & " / US " & INDEX('[1]Размерная сетка'!$C$2:$C$40,MATCH('[1]Основной сток'!J13,'[1]Размерная сетка'!$A$2:$A$40,0)) & " / см " & INDEX('[1]Размерная сетка'!$D$2:$D$40,MATCH('[1]Основной сток'!J13,'[1]Размерная сетка'!$A$2:$A$40,0)) & CHAR(10) & "• Посадка: размер в размер" & CHAR(10) & CHAR(10) & "🚚 Авито Доставка — по всей России" & CHAR(10) & "📍 Самовывоз — Москва, м. Тульская, Даниловская мануфактура" & CHAR(10) & CHAR(10) & "По любым вопросам пишите в личные сообщения — все расскажем и поможем выбрать размер 👟" -> Nike Dunk Low Easter 2022 (W), DD1503-001 • В наличии в Москве • Оригинал, можно проверить при получении • Совершенно новые, полный комплект • Размер: EU 38,5 / RU 37,5 / US 7,5 / см 24 • Посадка: размер в размер 🚚 Авито Доставка — по всей России 📍 Самовывоз — Москва, м. Тульская, Даниловская мануфактура По любым вопросам пишите в личные сообщения — все расскажем и поможем выбрать размер 👟 | H16: ='[1]Основной сток'!L13 -> 10000 | I16: {=VLOOKUP(INDEX('[1]Основной сток'!H:H,ROW()-3),[1]Фотки!A:B,2,FALSE)} -> https://i.ibb.co/spL5tx4t/1-1.jpg | J16: В сообщениях | K16: Одежда, обувь, аксессуары | L16: =IF(U16<=40,"Женская обувь","Мужская обувь") -> Женская обувь | M16: Новое с биркой | N16: Товар приобретен на продажу | O16: =PROPER('[1]Основной сток'!F13) -> Nike | P16: ='[1]Основной сток'!M13 -> Розовый | R16: Натуральная кожа | S16: Да | T16: =IF(L16="Мужская обувь","Кроссовки","Кроссовки и кеды") -> Кроссовки и кеды | U16: ='[1]Основной сток'!J13 - 1 -> 37.5 | V16: sold twice | X16: Активно | Y16: soldsoldtwice@gmail.com
A17: ='[1]Основной сток'!A14 -> 1342290 | B17: Package | D17: 79030042191 | E17: Варшавское ш., 9с1 | F17: =PROPER(LEFT('[1]Основной сток'!I14,FIND(CHAR(10),'[1]Основной сток'!I14&CHAR(10))-1)) -> Nike Dunk Low Easter 2022 (W) | G17: =F17 & ", " & '[1]Основной сток'!H14 & CHAR(10) & "• В наличии в Москве" & CHAR(10) & "• Оригинал, можно проверить при получении" & CHAR(10) & "• Совершенно новые, полный комплект" & CHAR(10) & "• Размер: EU " & '[1]Основной сток'!J14 & " / RU " & INDEX('[1]Размерная сетка'!$B$2:$B$40,MATCH('[1]Основной сток'!J14,'[1]Размерная сетка'!$A$2:$A$40,0)) & " / US " & INDEX('[1]Размерная сетка'!$C$2:$C$40,MATCH('[1]Основной сток'!J14,'[1]Размерная сетка'!$A$2:$A$40,0)) & " / см " & INDEX('[1]Размерная сетка'!$D$2:$D$40,MATCH('[1]Основной сток'!J14,'[1]Размерная сетка'!$A$2:$A$40,0)) & CHAR(10) & "• Посадка: размер в размер" & CHAR(10) & CHAR(10) & "🚚 Авито Доставка — по всей России" & CHAR(10) & "📍 Самовывоз — Москва, м. Тульская, Даниловская мануфактура" & CHAR(10) & CHAR(10) & "По любым вопросам пишите в личные сообщения — все расскажем и поможем выбрать размер 👟" -> Nike Dunk Low Easter 2022 (W), DD1503-001 • В наличии в Москве • Оригинал, можно проверить при получении • Совершенно новые, полный комплект • Размер: EU 39 / RU 38 / US 8 / см 24,5 • Посадка: размер в размер 🚚 Авито Доставка — по всей России 📍 Самовывоз — Москва, м. Тульская, Даниловская мануфактура По любым вопросам пишите в личные сообщения — все расскажем и поможем выбрать размер 👟 | H17: ='[1]Основной сток'!L14 -> 10000 | I17: {=VLOOKUP(INDEX('[1]Основной сток'!H:H,ROW()-3),[1]Фотки!A:B,2,FALSE)} -> https://i.ibb.co/spL5tx4t/1-1.jpg | J17: В сообщениях | K17: Одежда, обувь, аксессуары | L17: =IF(U17<=40,"Женская обувь","Мужская обувь") -> Женская обувь | M17: Новое с биркой | N17: Товар приобретен на продажу | O17: =PROPER('[1]Основной сток'!F14) -> Nike | P17: ='[1]Основной сток'!M14 -> Розовый | R17: Натуральная кожа | S17: Да | T17: =IF(L17="Мужская обувь","Кроссовки","Кроссовки и кеды") -> Кроссовки и кеды | U17: ='[1]Основной сток'!J14 - 1 -> 38 | V17: sold twice | X17: Активно | Y17: soldsoldtwice@gmail.com
A18: ='[1]Основной сток'!A15 -> 1342310 | B18: Package | D18: 79030042191 | E18: Варшавское ш., 9с1 | F18: =PROPER(LEFT('[1]Основной сток'!I15,FIND(CHAR(10),'[1]Основной сток'!I15&CHAR(10))-1)) -> Nike Dunk Low Next Nature White Black (W) | G18: =F18 & ", " & '[1]Основной сток'!H15 & CHAR(10) & "• В наличии в Москве" & CHAR(10) & "• Оригинал, можно проверить при получении" & CHAR(10) & "• Совершенно новые, полный комплект" & CHAR(10) & "• Размер: EU " & '[1]Основной сток'!J15 & " / RU " & INDEX('[1]Размерная сетка'!$B$2:$B$40,MATCH('[1]Основной сток'!J15,'[1]Размерная сетка'!$A$2:$A$40,0)) & " / US " & INDEX('[1]Размерная сетка'!$C$2:$C$40,MATCH('[1]Основной сток'!J15,'[1]Размерная сетка'!$A$2:$A$40,0)) & " / см " & INDEX('[1]Размерная сетка'!$D$2:$D$40,MATCH('[1]Основной сток'!J15,'[1]Размерная сетка'!$A$2:$A$40,0)) & CHAR(10) & "• Посадка: размер в размер" & CHAR(10) & CHAR(10) & "🚚 Авито Доставка — по всей России" & CHAR(10) & "📍 Самовывоз — Москва, м. Тульская, Даниловская мануфактура" & CHAR(10) & CHAR(10) & "По любым вопросам пишите в личные сообщения — все расскажем и поможем выбрать размер 👟" -> Nike Dunk Low Next Nature White Black (W), DD1873-102 • В наличии в Москве • Оригинал, можно проверить при получении • Совершенно новые, полный комплект • Размер: EU 38 / RU 37 / US 7 / см 23,5 • Посадка: размер в размер 🚚 Авито Доставка — по всей России 📍 Самовывоз — Москва, м. Тульская, Даниловская мануфактура По любым вопросам пишите в личные сообщения — все расскажем и поможем выбрать размер 👟 | H18: ='[1]Основной сток'!L15 -> 10000 | I18: {=VLOOKUP(INDEX('[1]Основной сток'!H:H,ROW()-3),[1]Фотки!A:B,2,FALSE)} -> https://i.ibb.co/XZ2qjJ41/1.jpg|https://i.ibb.co/vCDpSzgv/2.jpg|https://i.ibb.co/SXjGXVvm/3.jpg|https://i.ibb.co/XxdGGj8C/4.jpg | J18: В сообщениях | K18: Одежда, обувь, аксессуары | L18: =IF(U18<=40,"Женская обувь","Мужская обувь") -> Женская обувь | M18: Новое с биркой | N18: Товар приобретен на продажу | O18: =PROPER('[1]Основной сток'!F15) -> Nike | P18: ='[1]Основной сток'!M15 -> Черный | R18: Натуральная кожа | S18: Да | T18: =IF(L18="Мужская обувь","Кроссовки","Кроссовки и кеды") -> Кроссовки и кеды | U18: ='[1]Основной сток'!J15 - 1 -> 37 | V18: sold twice | X18: Активно | Y18: soldsoldtwice@gmail.com
... A395: ='[1]Основной сток'!A392 -> 3492896 | B395: Package | D395: 79030042191 | E395: Варшавское ш., 9с1 | F395: =PROPER(LEFT('[1]Основной сток'!I392,FIND(CHAR(10),'[1]Основной сток'!I392&CHAR(10))-1)) -> New Balance 530 'White Metallic Silver' | G395: =F395 & ", " & '[1]Основной сток'!H392 & CHAR(10) & "• В наличии в Москве" & CHAR(10) & "• Оригинал, можно проверить при получении" & CHAR(10) & "• Совершенно новые, полный комплект" & CHAR(10) & "• Размер: EU " & '[1]Основной сток'!J392 & " / RU " & INDEX('[1]Размерная сетка'!$B$2:$B$40,MATCH('[1]Основной сток'!J392,'[1]Размерная сетка'!$A$2:$A$40,0)) & " / US " & INDEX('[1]Размерная сетка'!$C$2:$C$40,MATCH('[1]Основной сток'!J392,'[1]Размерная сетка'!$A$2:$A$40,0)) & " / см " & INDEX('[1]Размерная сетка'!$D$2:$D$40,MATCH('[1]Основной сток'!J392,'[1]Размерная сетка'!$A$2:$A$40,0)) & CHAR(10) & "• Посадка: размер в размер" & CHAR(10) & CHAR(10) & "🚚 Авито Доставка — по всей России" & CHAR(10) & "📍 Самовывоз — Москва, м. Тульская, Даниловская мануфактура" & CHAR(10) & CHAR(10) & "По любым вопросам пишите в личные сообщения — все расскажем и поможем выбрать размер 👟" -> New Balance 530 'White Metallic Silver', MR530AD • В наличии в Москве • Оригинал, можно проверить при получении • Совершенно новые, полный комплект • Размер: EU 42 / RU 41 / US 8,5 / см 26,3 • Посадка: размер в размер 🚚 Авито Доставка — по всей России 📍 Самовывоз — Москва, м. Тульская, Даниловская мануфактура По любым вопросам пишите в личные сообщения — все расскажем и поможем выбрать размер 👟 | H395: ='[1]Основной сток'!L392 -> 9300 | I395: {=VLOOKUP(INDEX('[1]Основной сток'!H:H,ROW()-3),[1]Фотки!A:B,2,FALSE)} -> https://i.ibb.co/4wKV8NY1/1-1.jpg|https://i.ibb.co/vCmtcQ9n/2.jpg|https://i.ibb.co/fJBrkTV/3.jpg|https://i.ibb.co/GfDCmjh4/4.jpg | J395: В сообщениях | K395: Одежда, обувь, аксессуары | L395: =IF(U395<=40,"Женская обувь","Мужская обувь") -> Мужская обувь | M395: Новое с биркой | N395: Товар приобретен на продажу | O395: =PROPER('[1]Основной сток'!F392) -> New Balance | P395: ='[1]Основной сток'!M392 -> Белый | R395: Натуральная кожа | S395: Да | T395: =IF(L395="Мужская обувь","Кроссовки","Кроссовки и кеды") -> Кроссовки | U395: ='[1]Основной сток'!J392 - 1 -> 41 | V395: sold twice | X395: Активно | Y395: soldsoldtwice@gmail.com
